quartic_transformer/__init__.py
quartic_transformer/multi_stream_transformer.py
quartic_transformer/quartic_transformer.py
quartic_transformer/relational_transformer.py
quartic_transformer-0.0.18.dist-info/licenses/LICENSE
quartic_transformer-0.0.18.dist-info/METADATA
quartic_transformer-0.0.18.dist-info/WHEEL
quartic_transformer-0.0.18.dist-info/top_level.txt
quartic_transformer-0.0.18.dist-info/RECORD
