Metadata-Version: 2.4
Name: quartic-transformer
Version: 0.0.18
Summary: Quartic Transformer
Home-page: https://github.com/lucidrains/quartic-transformer
Author: Phil Wang
Author-email: lucidrains@gmail.com
License: MIT
Keywords: artificial intelligence,deep learning,transformer,attention
Classifier: Development Status :: 4 - Beta
Classifier: Intended Audience :: Developers
Classifier: Topic :: Scientific/Engineering :: Artificial Intelligence
Classifier: License :: OSI Approved :: MIT License
Classifier: Programming Language :: Python :: 3.6
License-File: LICENSE
Requires-Dist: colt5-attention
Requires-Dist: einops>=0.7.0
Requires-Dist: einx[torch]>=0.1.3
Requires-Dist: hyper-connections>=0.1.15
Requires-Dist: taylor-series-linear-attention
Requires-Dist: torch>=2.0
Requires-Dist: x-transformers
Dynamic: author
Dynamic: author-email
Dynamic: classifier
Dynamic: description-content-type
Dynamic: home-page
Dynamic: keywords
Dynamic: license
Dynamic: license-file
Dynamic: requires-dist
Dynamic: summary
